leider/__init__.py
leider/cli.py
leider/config.py
leider/docker_utils.py
leider/services.py
leider-0.3.0.dist-info/LICENSE
leider-0.3.0.dist-info/METADATA
leider-0.3.0.dist-info/WHEEL
leider-0.3.0.dist-info/entry_points.txt
leider-0.3.0.dist-info/top_level.txt
leider-0.3.0.dist-info/RECORD
