Metadata-Version: 2.1
Name: leider
Version: 0.3.0
Summary: Manages services in Docker for all your local apps.
Home-page: https://github.com/holmars/leider
Author: Hólmar Sigmundsson
Author-email: holmars@gmail.com
License: MIT
Platform: UNKNOWN
Classifier: Programming Language :: Python
Classifier: Programming Language :: Python :: 3.8
Classifier: Programming Language :: Python :: Implementation :: CPython
Requires-Dist: click
Requires-Dist: crayons
Requires-Dist: docker
Requires-Dist: ruamel.yaml
